kyanitapi/__init__.py
kyanitapi/_version.py
kyanitapi/find_kyanit.py
kyanitapi-1.0.1.dist-info/LICENSE
kyanitapi-1.0.1.dist-info/METADATA
kyanitapi-1.0.1.dist-info/WHEEL
kyanitapi-1.0.1.dist-info/top_level.txt
kyanitapi-1.0.1.dist-info/RECORD
