Metadata-Version: 2.1
Name: kyanitapi
Version: 1.0.1
Summary: Python API for Kyanit
Home-page: https://github.com/kyanit-project/kyanitapi
Author: Zsolt Nagy
Author-email: zsolt@kyanit.eu
License: GPLv3
Platform: UNKNOWN
Classifier: Programming Language :: Python :: 3
Classifier: License :: OSI Approved :: GNU General Public License v3 (GPLv3)
Classifier: Intended Audience :: Developers
Classifier: Operating System :: OS Independent
Requires-Python: >=3.8
Requires-Dist: psutil (<6,>=5)
Requires-Dist: pythonping (<2,>=1)
Requires-Dist: requests (<3,>=2)
